jsqlib/__init__.py
jsqlib/core.py
jsqlib/engine.py
jsqlib/helpers/__init__.py
jsqlib/helpers/common.py
jsqlib/helpers/constants.py
jsqlib/helpers/types.py
jsqlib-0.10a0.dist-info/METADATA
jsqlib-0.10a0.dist-info/WHEEL
jsqlib-0.10a0.dist-info/RECORD
