Metadata-Version: 2.3
Name: jsqlib
Version: 0.10a0
Summary: JSON to SQL query generator
License: MPL-2.0
Keywords: sql,json
Author: pymancer
Author-email: pymancer@gmail.com
Requires-Python: >=3.9,<3.13
Classifier: Development Status :: 3 - Alpha
Classifier: Environment :: Console
Classifier: Intended Audience :: Information Technology
Classifier: License :: OSI Approved
Classifier: License :: OSI Approved :: Mozilla Public License 2.0 (MPL 2.0)
Classifier: Operating System :: OS Independent
Classifier: Programming Language :: Python :: 3
Classifier: Programming Language :: Python :: 3.9
Classifier: Programming Language :: Python :: 3.10
Classifier: Programming Language :: Python :: 3.11
Classifier: Programming Language :: Python :: 3.12
Classifier: Topic :: Database
Classifier: Topic :: Software Development :: Libraries
Requires-Dist: jsonschema (>=4,<5)
Requires-Dist: python-box (>=5,<8)
Requires-Dist: sqlfluff (>=3,<4)
Project-URL: Documentation, https://gitlab.com/ru-r5/jsqlib/-/wikis/home
Project-URL: Homepage, https://gitlab.com/ru-r5/jsqlib
Project-URL: Repository, https://gitlab.com/ru-r5/jsqlib
